{
  "label": "8",
  "timestamp": 1772384620772,
  "canvasWidth": 759,
  "canvasHeight": 794,
  "strokes": [
    [
      {
        "x": 374.983,
        "y": 156.316,
        "t": 1
      },
      {
        "x": 367.34,
        "y": 155.778,
        "t": 15
      },
      {
        "x": 353.422,
        "y": 151.066,
        "t": 29
      },
      {
        "x": 327.196,
        "y": 156.52,
        "t": 47
      },
      {
        "x": 306.872,
        "y": 160.126,
        "t": 65
      },
      {
        "x": 291.935,
        "y": 173.264,
        "t": 82
      },
      {
        "x": 282.58,
        "y": 190.309,
        "t": 101
      },
      {
        "x": 279.248,
        "y": 213.806,
        "t": 119
      },
      {
        "x": 273.556,
        "y": 244.348,
        "t": 137
      },
      {
        "x": 288.519,
        "y": 318.564,
        "t": 152
      },
      {
        "x": 310.974,
        "y": 372.601,
        "t": 168
      },
      {
        "x": 337.417,
        "y": 427.686,
        "t": 183
      },
      {
        "x": 353.099,
        "y": 469.649,
        "t": 200
      },
      {
        "x": 366.489,
        "y": 505.497,
        "t": 217
      },
      {
        "x": 368.973,
        "y": 525.764,
        "t": 231
      },
      {
        "x": 364.866,
        "y": 539.8,
        "t": 246
      },
      {
        "x": 364.321,
        "y": 542.332,
        "t": 262
      },
      {
        "x": 362.076,
        "y": 545.305,
        "t": 279
      },
      {
        "x": 355.077,
        "y": 543.557,
        "t": 294
      },
      {
        "x": 341.787,
        "y": 545.441,
        "t": 314
      },
      {
        "x": 306.826,
        "y": 536.867,
        "t": 331
      },
      {
        "x": 236.16,
        "y": 502.576,
        "t": 346
      },
      {
        "x": 191.751,
        "y": 468.735,
        "t": 365
      },
      {
        "x": 167.551,
        "y": 451.647,
        "t": 382
      },
      {
        "x": 152.828,
        "y": 433.722,
        "t": 399
      },
      {
        "x": 143.307,
        "y": 415.985,
        "t": 414
      },
      {
        "x": 146.631,
        "y": 400.402,
        "t": 432
      },
      {
        "x": 146.406,
        "y": 385.815,
        "t": 447
      },
      {
        "x": 160.28,
        "y": 373.438,
        "t": 463
      },
      {
        "x": 184.43,
        "y": 358.534,
        "t": 480
      },
      {
        "x": 216.831,
        "y": 351.034,
        "t": 495
      },
      {
        "x": 294.499,
        "y": 336.727,
        "t": 513
      },
      {
        "x": 344.347,
        "y": 330.82,
        "t": 529
      },
      {
        "x": 384.305,
        "y": 324.457,
        "t": 546
      },
      {
        "x": 415.055,
        "y": 314.705,
        "t": 561
      },
      {
        "x": 438.688,
        "y": 313.292,
        "t": 578
      },
      {
        "x": 452.835,
        "y": 306.937,
        "t": 596
      },
      {
        "x": 464.723,
        "y": 295.711,
        "t": 615
      },
      {
        "x": 472.885,
        "y": 286.092,
        "t": 630
      },
      {
        "x": 476.937,
        "y": 276.969,
        "t": 645
      },
      {
        "x": 481.279,
        "y": 262.096,
        "t": 659
      },
      {
        "x": 482.599,
        "y": 253.09,
        "t": 677
      },
      {
        "x": 483.309,
        "y": 241.204,
        "t": 694
      },
      {
        "x": 486.476,
        "y": 232.63,
        "t": 709
      },
      {
        "x": 484.849,
        "y": 223.014,
        "t": 725
      },
      {
        "x": 480.767,
        "y": 218.126,
        "t": 740
      },
      {
        "x": 472.969,
        "y": 208.248,
        "t": 755
      },
      {
        "x": 462.919,
        "y": 202.623,
        "t": 771
      },
      {
        "x": 455.32,
        "y": 196.965,
        "t": 788
      },
      {
        "x": 438.723,
        "y": 188.351,
        "t": 804
      },
      {
        "x": 425.913,
        "y": 186.394,
        "t": 820
      },
      {
        "x": 414.444,
        "y": 180.888,
        "t": 836
      },
      {
        "x": 403.964,
        "y": 179.923,
        "t": 853
      },
      {
        "x": 398.506,
        "y": 176.29,
        "t": 871
      },
      {
        "x": 390.758,
        "y": 175.103,
        "t": 886
      },
      {
        "x": 385.892,
        "y": 173.085,
        "t": 902
      },
      {
        "x": 379.917,
        "y": 168.121,
        "t": 921
      },
      {
        "x": 365.073,
        "y": 165.799,
        "t": 940
      },
      {
        "x": 353.724,
        "y": 158.298,
        "t": 958
      },
      {
        "x": 349.012,
        "y": 158.888,
        "t": 971
      },
      {
        "x": 348.078,
        "y": 156.429,
        "t": 990
      },
      {
        "x": 348.932,
        "y": 156.191,
        "t": 1008
      }
    ]
  ]
}