{
  "label": "8",
  "timestamp": 1772384620779,
  "canvasWidth": 759,
  "canvasHeight": 794,
  "strokes": [
    [
      {
        "x": 289.948,
        "y": 175.449,
        "t": 1
      },
      {
        "x": 282.598,
        "y": 179.586,
        "t": 16
      },
      {
        "x": 267.823,
        "y": 182.194,
        "t": 33
      },
      {
        "x": 250.972,
        "y": 191.421,
        "t": 52
      },
      {
        "x": 231.571,
        "y": 206.092,
        "t": 69
      },
      {
        "x": 223.964,
        "y": 220.58,
        "t": 87
      },
      {
        "x": 220.912,
        "y": 241.491,
        "t": 103
      },
      {
        "x": 222.741,
        "y": 262.017,
        "t": 119
      },
      {
        "x": 227.045,
        "y": 294.431,
        "t": 134
      },
      {
        "x": 268.794,
        "y": 353.663,
        "t": 150
      },
      {
        "x": 307.961,
        "y": 395.98,
        "t": 168
      },
      {
        "x": 348.349,
        "y": 432.8,
        "t": 184
      },
      {
        "x": 377.119,
        "y": 467.131,
        "t": 200
      },
      {
        "x": 395.629,
        "y": 491.952,
        "t": 218
      },
      {
        "x": 405.296,
        "y": 511.656,
        "t": 233
      },
      {
        "x": 410.222,
        "y": 527.103,
        "t": 251
      },
      {
        "x": 414.827,
        "y": 524.798,
        "t": 268
      },
      {
        "x": 407.698,
        "y": 530.334,
        "t": 284
      },
      {
        "x": 405.766,
        "y": 528.44,
        "t": 301
      },
      {
        "x": 389.882,
        "y": 538.035,
        "t": 320
      },
      {
        "x": 359.298,
        "y": 541.394,
        "t": 336
      },
      {
        "x": 282.176,
        "y": 534.843,
        "t": 355
      },
      {
        "x": 232.522,
        "y": 521.031,
        "t": 371
      },
      {
        "x": 203.472,
        "y": 511.697,
        "t": 389
      },
      {
        "x": 181.259,
        "y": 501.517,
        "t": 405
      },
      {
        "x": 172.631,
        "y": 488.632,
        "t": 424
      },
      {
        "x": 168.194,
        "y": 473.728,
        "t": 440
      },
      {
        "x": 166.373,
        "y": 462.846,
        "t": 455
      },
      {
        "x": 169.772,
        "y": 445.218,
        "t": 472
      },
      {
        "x": 190.365,
        "y": 423.706,
        "t": 489
      },
      {
        "x": 216.255,
        "y": 405.299,
        "t": 502
      },
      {
        "x": 280.204,
        "y": 368.671,
        "t": 521
      },
      {
        "x": 320.031,
        "y": 345.059,
        "t": 539
      },
      {
        "x": 356.646,
        "y": 326.528,
        "t": 559
      },
      {
        "x": 379.581,
        "y": 308.871,
        "t": 575
      },
      {
        "x": 398.173,
        "y": 296.819,
        "t": 593
      },
      {
        "x": 412.213,
        "y": 282.341,
        "t": 610
      },
      {
        "x": 418.768,
        "y": 269.725,
        "t": 625
      },
      {
        "x": 419.324,
        "y": 260.422,
        "t": 643
      },
      {
        "x": 426.279,
        "y": 250.128,
        "t": 660
      },
      {
        "x": 421.738,
        "y": 233.557,
        "t": 677
      },
      {
        "x": 416.352,
        "y": 228.152,
        "t": 692
      },
      {
        "x": 418.972,
        "y": 216.795,
        "t": 710
      },
      {
        "x": 415.614,
        "y": 210.108,
        "t": 726
      },
      {
        "x": 407.306,
        "y": 202.893,
        "t": 742
      },
      {
        "x": 404.613,
        "y": 196.477,
        "t": 757
      },
      {
        "x": 397.566,
        "y": 190.775,
        "t": 772
      },
      {
        "x": 385.304,
        "y": 189.577,
        "t": 788
      },
      {
        "x": 376.827,
        "y": 186.202,
        "t": 805
      },
      {
        "x": 361.849,
        "y": 185.37,
        "t": 823
      },
      {
        "x": 344.657,
        "y": 186.073,
        "t": 838
      },
      {
        "x": 336.835,
        "y": 183.653,
        "t": 855
      },
      {
        "x": 326.044,
        "y": 191.95,
        "t": 873
      },
      {
        "x": 318.354,
        "y": 192.559,
        "t": 891
      },
      {
        "x": 312.394,
        "y": 188.166,
        "t": 909
      },
      {
        "x": 304.614,
        "y": 188.963,
        "t": 923
      },
      {
        "x": 296.405,
        "y": 191.554,
        "t": 942
      },
      {
        "x": 282.131,
        "y": 191.536,
        "t": 960
      },
      {
        "x": 269.302,
        "y": 190.741,
        "t": 976
      },
      {
        "x": 268.38,
        "y": 188.13,
        "t": 992
      },
      {
        "x": 265.202,
        "y": 185.052,
        "t": 1012
      },
      {
        "x": 265.949,
        "y": 187.869,
        "t": 1028
      }
    ]
  ]
}