{
  "label": "\\\\div",
  "timestamp": 1772385284499,
  "canvasWidth": 759,
  "canvasHeight": 794,
  "strokes": [
    [
      {
        "x": 372.04,
        "y": 262.168,
        "t": 0
      },
      {
        "x": 372.289,
        "y": 260.293,
        "t": 23
      },
      {
        "x": 382.726,
        "y": 260.56,
        "t": 40
      },
      {
        "x": 392.621,
        "y": 255.796,
        "t": 57
      },
      {
        "x": 404.173,
        "y": 254.831,
        "t": 74
      },
      {
        "x": 420.283,
        "y": 255.473,
        "t": 93
      },
      {
        "x": 448.477,
        "y": 255.675,
        "t": 109
      },
      {
        "x": 482.105,
        "y": 257.385,
        "t": 127
      },
      {
        "x": 517.93,
        "y": 256.653,
        "t": 143
      },
      {
        "x": 549.558,
        "y": 259.157,
        "t": 159
      },
      {
        "x": 573.919,
        "y": 260.924,
        "t": 174
      },
      {
        "x": 587.968,
        "y": 264.365,
        "t": 193
      },
      {
        "x": 593.444,
        "y": 262.475,
        "t": 207
      }
    ],
    [
      {
        "x": 476.62,
        "y": 198.517,
        "t": 542
      },
      {
        "x": 478.41,
        "y": 196.8,
        "t": 624
      }
    ],
    [
      {
        "x": 463.151,
        "y": 338.686,
        "t": 1185
      },
      {
        "x": 464.129,
        "y": 342.673,
        "t": 1224
      },
      {
        "x": 464.92,
        "y": 340.836,
        "t": 1240
      },
      {
        "x": 468.254,
        "y": 342.544,
        "t": 1264
      },
      {
        "x": 466.758,
        "y": 340.182,
        "t": 1280
      },
      {
        "x": 467.496,
        "y": 339.361,
        "t": 1298
      },
      {
        "x": 465.276,
        "y": 340.457,
        "t": 1317
      }
    ]
  ]
}