{
  "label": "9",
  "timestamp": 1772384701207,
  "canvasWidth": 759,
  "canvasHeight": 794,
  "strokes": [
    [
      {
        "x": 236.482,
        "y": 186.912,
        "t": 0
      },
      {
        "x": 228.535,
        "y": 188.805,
        "t": 17
      },
      {
        "x": 216.427,
        "y": 184.835,
        "t": 33
      },
      {
        "x": 202.557,
        "y": 174.868,
        "t": 50
      },
      {
        "x": 179.647,
        "y": 164.21,
        "t": 65
      },
      {
        "x": 161.647,
        "y": 149.232,
        "t": 82
      },
      {
        "x": 140.07,
        "y": 141.921,
        "t": 98
      },
      {
        "x": 133.773,
        "y": 132.101,
        "t": 114
      },
      {
        "x": 131.013,
        "y": 122.641,
        "t": 130
      },
      {
        "x": 132.622,
        "y": 120.915,
        "t": 148
      },
      {
        "x": 133.191,
        "y": 112.618,
        "t": 162
      },
      {
        "x": 133.086,
        "y": 107.846,
        "t": 179
      },
      {
        "x": 131.204,
        "y": 99.188,
        "t": 195
      },
      {
        "x": 134.747,
        "y": 91.878,
        "t": 214
      },
      {
        "x": 140.009,
        "y": 78.346,
        "t": 227
      },
      {
        "x": 147.121,
        "y": 72.355,
        "t": 242
      },
      {
        "x": 154.536,
        "y": 67.888,
        "t": 260
      },
      {
        "x": 161.386,
        "y": 66.039,
        "t": 278
      },
      {
        "x": 177.313,
        "y": 61.41,
        "t": 295
      },
      {
        "x": 193.994,
        "y": 61.68,
        "t": 311
      },
      {
        "x": 209.922,
        "y": 57.841,
        "t": 329
      },
      {
        "x": 227.805,
        "y": 58.506,
        "t": 346
      },
      {
        "x": 238.377,
        "y": 58.987,
        "t": 365
      },
      {
        "x": 242.543,
        "y": 58.1,
        "t": 383
      },
      {
        "x": 246.631,
        "y": 59.926,
        "t": 400
      },
      {
        "x": 251.306,
        "y": 58.213,
        "t": 419
      },
      {
        "x": 253.577,
        "y": 62.185,
        "t": 435
      },
      {
        "x": 256.285,
        "y": 70.49,
        "t": 451
      },
      {
        "x": 261.615,
        "y": 76.325,
        "t": 468
      },
      {
        "x": 257.498,
        "y": 83.909,
        "t": 485
      },
      {
        "x": 261.557,
        "y": 96.188,
        "t": 501
      },
      {
        "x": 259.513,
        "y": 106.121,
        "t": 519
      },
      {
        "x": 261.422,
        "y": 120.366,
        "t": 535
      },
      {
        "x": 260.764,
        "y": 134.446,
        "t": 552
      },
      {
        "x": 258.025,
        "y": 152.801,
        "t": 569
      },
      {
        "x": 259.835,
        "y": 162.091,
        "t": 587
      },
      {
        "x": 249.55,
        "y": 174.32,
        "t": 602
      },
      {
        "x": 245.213,
        "y": 186.404,
        "t": 621
      },
      {
        "x": 241.235,
        "y": 195.567,
        "t": 637
      },
      {
        "x": 237.769,
        "y": 199.534,
        "t": 651
      },
      {
        "x": 230.266,
        "y": 208.787,
        "t": 667
      },
      {
        "x": 224.037,
        "y": 213.549,
        "t": 684
      },
      {
        "x": 216.744,
        "y": 220.048,
        "t": 703
      },
      {
        "x": 210.723,
        "y": 226.739,
        "t": 719
      },
      {
        "x": 196.957,
        "y": 237.482,
        "t": 735
      },
      {
        "x": 183.796,
        "y": 242.127,
        "t": 749
      },
      {
        "x": 176.224,
        "y": 250.095,
        "t": 766
      },
      {
        "x": 163.001,
        "y": 259.803,
        "t": 782
      },
      {
        "x": 153.572,
        "y": 267.487,
        "t": 797
      },
      {
        "x": 145.263,
        "y": 273.501,
        "t": 811
      },
      {
        "x": 134.678,
        "y": 284.598,
        "t": 825
      },
      {
        "x": 127.686,
        "y": 285.27,
        "t": 842
      },
      {
        "x": 124.521,
        "y": 284.813,
        "t": 858
      }
    ]
  ]
}