{
  "label": "9",
  "timestamp": 1772384700018,
  "canvasWidth": 759,
  "canvasHeight": 794,
  "strokes": [
    [
      {
        "x": 517.339,
        "y": 157.912,
        "t": 0
      },
      {
        "x": 493.529,
        "y": 159.49,
        "t": 18
      },
      {
        "x": 479.695,
        "y": 161.604,
        "t": 35
      },
      {
        "x": 467.481,
        "y": 167.508,
        "t": 54
      },
      {
        "x": 456.631,
        "y": 186.711,
        "t": 71
      },
      {
        "x": 455.853,
        "y": 202.667,
        "t": 88
      },
      {
        "x": 457.203,
        "y": 224.545,
        "t": 105
      },
      {
        "x": 461.885,
        "y": 240.208,
        "t": 122
      },
      {
        "x": 465.938,
        "y": 257.0,
        "t": 136
      },
      {
        "x": 474.265,
        "y": 265.41,
        "t": 152
      },
      {
        "x": 479.689,
        "y": 267.618,
        "t": 170
      },
      {
        "x": 489.067,
        "y": 264.223,
        "t": 188
      },
      {
        "x": 495.342,
        "y": 262.63,
        "t": 205
      },
      {
        "x": 498.379,
        "y": 261.331,
        "t": 223
      },
      {
        "x": 505.656,
        "y": 258.204,
        "t": 237
      },
      {
        "x": 508.882,
        "y": 250.532,
        "t": 251
      },
      {
        "x": 512.634,
        "y": 240.227,
        "t": 265
      },
      {
        "x": 518.596,
        "y": 225.46,
        "t": 281
      },
      {
        "x": 522.967,
        "y": 204.811,
        "t": 299
      },
      {
        "x": 521.599,
        "y": 183.939,
        "t": 314
      },
      {
        "x": 521.805,
        "y": 167.227,
        "t": 329
      },
      {
        "x": 521.402,
        "y": 154.836,
        "t": 346
      },
      {
        "x": 520.704,
        "y": 151.704,
        "t": 364
      },
      {
        "x": 519.815,
        "y": 148.912,
        "t": 382
      },
      {
        "x": 521.776,
        "y": 150.444,
        "t": 519
      },
      {
        "x": 520.405,
        "y": 151.619,
        "t": 586
      },
      {
        "x": 524.483,
        "y": 166.877,
        "t": 601
      },
      {
        "x": 536.079,
        "y": 207.248,
        "t": 617
      },
      {
        "x": 549.806,
        "y": 267.302,
        "t": 634
      },
      {
        "x": 571.58,
        "y": 341.22,
        "t": 651
      },
      {
        "x": 583.211,
        "y": 400.539,
        "t": 669
      },
      {
        "x": 592.567,
        "y": 430.699,
        "t": 685
      },
      {
        "x": 596.384,
        "y": 441.811,
        "t": 702
      }
    ]
  ]
}