{
  "label": "3",
  "timestamp": 1772364283218,
  "canvasWidth": 1528,
  "canvasHeight": 779,
  "strokes": [
    [
      {
        "x": 746,
        "y": 251,
        "t": 0
      },
      {
        "x": 747,
        "y": 250,
        "t": 172
      },
      {
        "x": 752,
        "y": 246,
        "t": 185
      },
      {
        "x": 757,
        "y": 243,
        "t": 193
      },
      {
        "x": 761,
        "y": 241,
        "t": 201
      },
      {
        "x": 765,
        "y": 239,
        "t": 210
      },
      {
        "x": 772,
        "y": 236,
        "t": 218
      },
      {
        "x": 775,
        "y": 235,
        "t": 226
      },
      {
        "x": 778,
        "y": 235,
        "t": 235
      },
      {
        "x": 779,
        "y": 235,
        "t": 243
      },
      {
        "x": 781,
        "y": 236,
        "t": 251
      },
      {
        "x": 783,
        "y": 238,
        "t": 260
      },
      {
        "x": 784,
        "y": 239,
        "t": 268
      },
      {
        "x": 786,
        "y": 242,
        "t": 276
      },
      {
        "x": 786,
        "y": 246,
        "t": 285
      },
      {
        "x": 787,
        "y": 250,
        "t": 293
      },
      {
        "x": 787,
        "y": 257,
        "t": 301
      },
      {
        "x": 785,
        "y": 263,
        "t": 310
      },
      {
        "x": 783,
        "y": 270,
        "t": 318
      },
      {
        "x": 778,
        "y": 277,
        "t": 326
      },
      {
        "x": 766,
        "y": 290,
        "t": 335
      },
      {
        "x": 759,
        "y": 297,
        "t": 343
      },
      {
        "x": 754,
        "y": 299,
        "t": 352
      },
      {
        "x": 748,
        "y": 302,
        "t": 360
      },
      {
        "x": 744,
        "y": 305,
        "t": 368
      },
      {
        "x": 740,
        "y": 306,
        "t": 376
      },
      {
        "x": 738,
        "y": 307,
        "t": 385
      },
      {
        "x": 738,
        "y": 307,
        "t": 393
      },
      {
        "x": 737,
        "y": 307,
        "t": 401
      },
      {
        "x": 736,
        "y": 307,
        "t": 418
      },
      {
        "x": 738,
        "y": 306,
        "t": 459
      },
      {
        "x": 740,
        "y": 305,
        "t": 469
      },
      {
        "x": 745,
        "y": 304,
        "t": 476
      },
      {
        "x": 750,
        "y": 302,
        "t": 485
      },
      {
        "x": 758,
        "y": 301,
        "t": 493
      },
      {
        "x": 765,
        "y": 300,
        "t": 501
      },
      {
        "x": 770,
        "y": 300,
        "t": 510
      },
      {
        "x": 775,
        "y": 300,
        "t": 518
      },
      {
        "x": 779,
        "y": 300,
        "t": 526
      },
      {
        "x": 784,
        "y": 300,
        "t": 535
      },
      {
        "x": 790,
        "y": 305,
        "t": 543
      },
      {
        "x": 794,
        "y": 308,
        "t": 551
      },
      {
        "x": 795,
        "y": 311,
        "t": 560
      },
      {
        "x": 797,
        "y": 316,
        "t": 568
      },
      {
        "x": 798,
        "y": 320,
        "t": 576
      },
      {
        "x": 798,
        "y": 324,
        "t": 585
      },
      {
        "x": 798,
        "y": 330,
        "t": 593
      },
      {
        "x": 796,
        "y": 334,
        "t": 601
      },
      {
        "x": 793,
        "y": 339,
        "t": 610
      },
      {
        "x": 789,
        "y": 345,
        "t": 618
      },
      {
        "x": 785,
        "y": 350,
        "t": 627
      },
      {
        "x": 780,
        "y": 356,
        "t": 635
      },
      {
        "x": 766,
        "y": 363,
        "t": 643
      },
      {
        "x": 759,
        "y": 366,
        "t": 651
      },
      {
        "x": 753,
        "y": 369,
        "t": 660
      },
      {
        "x": 746,
        "y": 370,
        "t": 668
      },
      {
        "x": 738,
        "y": 371,
        "t": 676
      },
      {
        "x": 732,
        "y": 372,
        "t": 684
      },
      {
        "x": 729,
        "y": 372,
        "t": 693
      },
      {
        "x": 723,
        "y": 372,
        "t": 701
      },
      {
        "x": 718,
        "y": 371,
        "t": 710
      },
      {
        "x": 714,
        "y": 370,
        "t": 718
      },
      {
        "x": 709,
        "y": 369,
        "t": 726
      },
      {
        "x": 706,
        "y": 368,
        "t": 734
      },
      {
        "x": 701,
        "y": 364,
        "t": 743
      },
      {
        "x": 698,
        "y": 362,
        "t": 751
      }
    ]
  ]
}