{
  "label": "1",
  "timestamp": 1770830882549,
  "canvasWidth": 1528,
  "canvasHeight": 779,
  "strokes": [
    [
      {
        "x": 252,
        "y": 697,
        "t": 0
      },
      {
        "x": 253,
        "y": 697,
        "t": 210
      },
      {
        "x": 257,
        "y": 697,
        "t": 217
      },
      {
        "x": 262,
        "y": 697,
        "t": 225
      },
      {
        "x": 266,
        "y": 698,
        "t": 233
      },
      {
        "x": 271,
        "y": 699,
        "t": 240
      },
      {
        "x": 275,
        "y": 699,
        "t": 248
      },
      {
        "x": 280,
        "y": 700,
        "t": 256
      },
      {
        "x": 284,
        "y": 701,
        "t": 264
      },
      {
        "x": 287,
        "y": 701,
        "t": 272
      },
      {
        "x": 290,
        "y": 702,
        "t": 280
      },
      {
        "x": 294,
        "y": 702,
        "t": 288
      },
      {
        "x": 298,
        "y": 702,
        "t": 297
      },
      {
        "x": 302,
        "y": 702,
        "t": 305
      },
      {
        "x": 307,
        "y": 703,
        "t": 313
      },
      {
        "x": 310,
        "y": 704,
        "t": 322
      },
      {
        "x": 315,
        "y": 704,
        "t": 330
      },
      {
        "x": 319,
        "y": 704,
        "t": 338
      },
      {
        "x": 324,
        "y": 705,
        "t": 347
      },
      {
        "x": 328,
        "y": 705,
        "t": 355
      },
      {
        "x": 331,
        "y": 705,
        "t": 363
      },
      {
        "x": 334,
        "y": 705,
        "t": 372
      },
      {
        "x": 338,
        "y": 705,
        "t": 380
      },
      {
        "x": 341,
        "y": 705,
        "t": 388
      },
      {
        "x": 342,
        "y": 705,
        "t": 403
      },
      {
        "x": 343,
        "y": 705,
        "t": 412
      },
      {
        "x": 344,
        "y": 705,
        "t": 465
      }
    ],
    [
      {
        "x": 250,
        "y": 586,
        "t": 1373
      },
      {
        "x": 250,
        "y": 583,
        "t": 1699
      },
      {
        "x": 254,
        "y": 580,
        "t": 1712
      },
      {
        "x": 256,
        "y": 575,
        "t": 1721
      },
      {
        "x": 259,
        "y": 570,
        "t": 1729
      },
      {
        "x": 266,
        "y": 561,
        "t": 1737
      },
      {
        "x": 270,
        "y": 558,
        "t": 1745
      },
      {
        "x": 273,
        "y": 553,
        "t": 1754
      },
      {
        "x": 274,
        "y": 550,
        "t": 1762
      },
      {
        "x": 277,
        "y": 548,
        "t": 1771
      },
      {
        "x": 278,
        "y": 547,
        "t": 1779
      },
      {
        "x": 278,
        "y": 547,
        "t": 1807
      },
      {
        "x": 278,
        "y": 546,
        "t": 1814
      },
      {
        "x": 279,
        "y": 546,
        "t": 1838
      },
      {
        "x": 279,
        "y": 546,
        "t": 1985
      },
      {
        "x": 280,
        "y": 549,
        "t": 1999
      },
      {
        "x": 282,
        "y": 553,
        "t": 2007
      },
      {
        "x": 282,
        "y": 557,
        "t": 2014
      },
      {
        "x": 282,
        "y": 564,
        "t": 2022
      },
      {
        "x": 283,
        "y": 570,
        "t": 2031
      },
      {
        "x": 284,
        "y": 576,
        "t": 2039
      },
      {
        "x": 284,
        "y": 585,
        "t": 2047
      },
      {
        "x": 284,
        "y": 590,
        "t": 2056
      },
      {
        "x": 284,
        "y": 598,
        "t": 2064
      },
      {
        "x": 284,
        "y": 606,
        "t": 2072
      },
      {
        "x": 284,
        "y": 613,
        "t": 2081
      },
      {
        "x": 284,
        "y": 621,
        "t": 2089
      },
      {
        "x": 284,
        "y": 627,
        "t": 2097
      },
      {
        "x": 284,
        "y": 631,
        "t": 2106
      },
      {
        "x": 285,
        "y": 638,
        "t": 2114
      },
      {
        "x": 285,
        "y": 644,
        "t": 2122
      },
      {
        "x": 285,
        "y": 650,
        "t": 2131
      },
      {
        "x": 285,
        "y": 653,
        "t": 2139
      },
      {
        "x": 285,
        "y": 654,
        "t": 2148
      },
      {
        "x": 285,
        "y": 656,
        "t": 2156
      },
      {
        "x": 286,
        "y": 656,
        "t": 2164
      },
      {
        "x": 286,
        "y": 657,
        "t": 2176
      },
      {
        "x": 286,
        "y": 658,
        "t": 2200
      },
      {
        "x": 286,
        "y": 658,
        "t": 2263
      },
      {
        "x": 286,
        "y": 660,
        "t": 2270
      },
      {
        "x": 286,
        "y": 661,
        "t": 2278
      },
      {
        "x": 286,
        "y": 662,
        "t": 2287
      },
      {
        "x": 286,
        "y": 664,
        "t": 2294
      },
      {
        "x": 286,
        "y": 666,
        "t": 2302
      },
      {
        "x": 286,
        "y": 668,
        "t": 2308
      },
      {
        "x": 286,
        "y": 669,
        "t": 2316
      },
      {
        "x": 286,
        "y": 670,
        "t": 2324
      },
      {
        "x": 286,
        "y": 672,
        "t": 2331
      },
      {
        "x": 286,
        "y": 673,
        "t": 2348
      },
      {
        "x": 286,
        "y": 673,
        "t": 2356
      },
      {
        "x": 286,
        "y": 674,
        "t": 2381
      },
      {
        "x": 286,
        "y": 674,
        "t": 2416
      },
      {
        "x": 287,
        "y": 675,
        "t": 2424
      },
      {
        "x": 287,
        "y": 677,
        "t": 2448
      },
      {
        "x": 287,
        "y": 678,
        "t": 2463
      },
      {
        "x": 287,
        "y": 678,
        "t": 2524
      },
      {
        "x": 288,
        "y": 679,
        "t": 2532
      },
      {
        "x": 288,
        "y": 680,
        "t": 2539
      },
      {
        "x": 289,
        "y": 680,
        "t": 2547
      },
      {
        "x": 289,
        "y": 681,
        "t": 2556
      },
      {
        "x": 289,
        "y": 682,
        "t": 2564
      },
      {
        "x": 289,
        "y": 682,
        "t": 2578
      },
      {
        "x": 290,
        "y": 682,
        "t": 2586
      },
      {
        "x": 290,
        "y": 683,
        "t": 2726
      },
      {
        "x": 290,
        "y": 684,
        "t": 2739
      },
      {
        "x": 290,
        "y": 685,
        "t": 2763
      },
      {
        "x": 290,
        "y": 686,
        "t": 2801
      },
      {
        "x": 290,
        "y": 687,
        "t": 2833
      },
      {
        "x": 291,
        "y": 690,
        "t": 2839
      },
      {
        "x": 291,
        "y": 691,
        "t": 2847
      },
      {
        "x": 292,
        "y": 694,
        "t": 2855
      },
      {
        "x": 292,
        "y": 698,
        "t": 2863
      },
      {
        "x": 292,
        "y": 702,
        "t": 2871
      },
      {
        "x": 293,
        "y": 705,
        "t": 2879
      },
      {
        "x": 294,
        "y": 707,
        "t": 2888
      },
      {
        "x": 294,
        "y": 710,
        "t": 2896
      },
      {
        "x": 294,
        "y": 711,
        "t": 2904
      },
      {
        "x": 295,
        "y": 713,
        "t": 2913
      },
      {
        "x": 296,
        "y": 714,
        "t": 2921
      },
      {
        "x": 297,
        "y": 714,
        "t": 2930
      },
      {
        "x": 298,
        "y": 714,
        "t": 2940
      },
      {
        "x": 299,
        "y": 714,
        "t": 2948
      },
      {
        "x": 300,
        "y": 713,
        "t": 2972
      },
      {
        "x": 300,
        "y": 712,
        "t": 3008
      }
    ]
  ]
}