{
  "label": "7",
  "timestamp": 1772384567437,
  "canvasWidth": 759,
  "canvasHeight": 794,
  "strokes": [
    [
      {
        "x": 240.796,
        "y": 101.22,
        "t": 0
      },
      {
        "x": 235.411,
        "y": 98.779,
        "t": 17
      },
      {
        "x": 224.815,
        "y": 98.918,
        "t": 37
      },
      {
        "x": 227.94,
        "y": 96.454,
        "t": 117
      },
      {
        "x": 235.111,
        "y": 100.84,
        "t": 124
      },
      {
        "x": 245.222,
        "y": 100.881,
        "t": 137
      },
      {
        "x": 281.064,
        "y": 108.346,
        "t": 153
      },
      {
        "x": 330.083,
        "y": 120.353,
        "t": 167
      },
      {
        "x": 380.099,
        "y": 130.028,
        "t": 183
      },
      {
        "x": 417.336,
        "y": 142.453,
        "t": 199
      },
      {
        "x": 439.034,
        "y": 148.974,
        "t": 213
      },
      {
        "x": 438.415,
        "y": 157.496,
        "t": 231
      },
      {
        "x": 442.125,
        "y": 162.402,
        "t": 244
      },
      {
        "x": 435.333,
        "y": 165.835,
        "t": 262
      },
      {
        "x": 432.329,
        "y": 201.407,
        "t": 277
      },
      {
        "x": 421.909,
        "y": 253.563,
        "t": 294
      },
      {
        "x": 394.205,
        "y": 325.448,
        "t": 310
      },
      {
        "x": 362.322,
        "y": 403.722,
        "t": 324
      },
      {
        "x": 330.258,
        "y": 475.272,
        "t": 343
      },
      {
        "x": 308.046,
        "y": 525.327,
        "t": 360
      },
      {
        "x": 282.65,
        "y": 563.426,
        "t": 379
      },
      {
        "x": 274.738,
        "y": 585.488,
        "t": 397
      },
      {
        "x": 265.838,
        "y": 598.807,
        "t": 414
      },
      {
        "x": 266.856,
        "y": 604.449,
        "t": 428
      },
      {
        "x": 257.885,
        "y": 600.069,
        "t": 538
      }
    ]
  ]
}