{
  "label": "/",
  "timestamp": 1772381667007,
  "canvasWidth": 1528,
  "canvasHeight": 779,
  "strokes": [
    [
      {
        "x": 317,
        "y": 237,
        "t": 0
      },
      {
        "x": 312,
        "y": 242,
        "t": 194
      },
      {
        "x": 306,
        "y": 250,
        "t": 202
      },
      {
        "x": 298,
        "y": 261,
        "t": 210
      },
      {
        "x": 291,
        "y": 270,
        "t": 218
      },
      {
        "x": 285,
        "y": 282,
        "t": 226
      },
      {
        "x": 278,
        "y": 290,
        "t": 234
      },
      {
        "x": 272,
        "y": 300,
        "t": 243
      },
      {
        "x": 266,
        "y": 309,
        "t": 252
      },
      {
        "x": 260,
        "y": 318,
        "t": 260
      },
      {
        "x": 255,
        "y": 327,
        "t": 268
      },
      {
        "x": 250,
        "y": 334,
        "t": 277
      },
      {
        "x": 245,
        "y": 341,
        "t": 284
      },
      {
        "x": 242,
        "y": 346,
        "t": 293
      },
      {
        "x": 240,
        "y": 348,
        "t": 301
      },
      {
        "x": 238,
        "y": 350,
        "t": 309
      },
      {
        "x": 238,
        "y": 350,
        "t": 317
      },
      {
        "x": 237,
        "y": 350,
        "t": 326
      }
    ]
  ]
}