{
  "label": "/",
  "timestamp": 1772443913053,
  "canvasWidth": 1528,
  "canvasHeight": 779,
  "strokes": [
    [
      {
        "x": 596,
        "y": 328,
        "t": 0
      },
      {
        "x": 594,
        "y": 334,
        "t": 211
      },
      {
        "x": 589,
        "y": 345,
        "t": 216
      },
      {
        "x": 582,
        "y": 356,
        "t": 224
      },
      {
        "x": 577,
        "y": 368,
        "t": 233
      },
      {
        "x": 571,
        "y": 379,
        "t": 240
      },
      {
        "x": 565,
        "y": 390,
        "t": 247
      },
      {
        "x": 559,
        "y": 401,
        "t": 255
      },
      {
        "x": 554,
        "y": 410,
        "t": 263
      },
      {
        "x": 550,
        "y": 420,
        "t": 271
      },
      {
        "x": 547,
        "y": 427,
        "t": 279
      },
      {
        "x": 543,
        "y": 433,
        "t": 287
      },
      {
        "x": 542,
        "y": 438,
        "t": 296
      },
      {
        "x": 541,
        "y": 441,
        "t": 304
      },
      {
        "x": 540,
        "y": 443,
        "t": 313
      },
      {
        "x": 539,
        "y": 444,
        "t": 321
      },
      {
        "x": 538,
        "y": 445,
        "t": 330
      },
      {
        "x": 538,
        "y": 446,
        "t": 338
      },
      {
        "x": 538,
        "y": 446,
        "t": 346
      }
    ]
  ]
}