{
  "label": "\\times",
  "timestamp": 1773052044428,
  "canvasWidth": 1536,
  "canvasHeight": 730,
  "strokes": [
    [
      {
        "x": 1327,
        "y": 559,
        "t": 0
      },
      {
        "x": 1327,
        "y": 559,
        "t": 2
      },
      {
        "x": 1326,
        "y": 559,
        "t": 61
      },
      {
        "x": 1325,
        "y": 558,
        "t": 68
      },
      {
        "x": 1322,
        "y": 556,
        "t": 75
      },
      {
        "x": 1316,
        "y": 551,
        "t": 83
      },
      {
        "x": 1309,
        "y": 547,
        "t": 89
      },
      {
        "x": 1299,
        "y": 541,
        "t": 100
      },
      {
        "x": 1290,
        "y": 535,
        "t": 115
      },
      {
        "x": 1280,
        "y": 527,
        "t": 123
      },
      {
        "x": 1266,
        "y": 519,
        "t": 130
      },
      {
        "x": 1249,
        "y": 511,
        "t": 136
      },
      {
        "x": 1232,
        "y": 504,
        "t": 144
      },
      {
        "x": 1213,
        "y": 495,
        "t": 172
      },
      {
        "x": 1213,
        "y": 495,
        "t": 252
      }
    ],
    [
      {
        "x": 1248,
        "y": 583,
        "t": 569
      },
      {
        "x": 1250,
        "y": 579,
        "t": 575
      },
      {
        "x": 1254,
        "y": 573,
        "t": 583
      },
      {
        "x": 1257,
        "y": 567,
        "t": 591
      },
      {
        "x": 1260,
        "y": 560,
        "t": 599
      },
      {
        "x": 1264,
        "y": 554,
        "t": 607
      },
      {
        "x": 1267,
        "y": 547,
        "t": 614
      },
      {
        "x": 1272,
        "y": 540,
        "t": 629
      },
      {
        "x": 1278,
        "y": 531,
        "t": 636
      },
      {
        "x": 1283,
        "y": 521,
        "t": 643
      },
      {
        "x": 1289,
        "y": 512,
        "t": 650
      },
      {
        "x": 1294,
        "y": 505,
        "t": 657
      },
      {
        "x": 1297,
        "y": 503,
        "t": 664
      },
      {
        "x": 1298,
        "y": 499,
        "t": 671
      },
      {
        "x": 1299,
        "y": 499,
        "t": 679
      },
      {
        "x": 1298,
        "y": 499,
        "t": 760
      },
      {
        "x": 1295,
        "y": 500,
        "t": 767
      },
      {
        "x": 1290,
        "y": 500,
        "t": 783
      },
      {
        "x": 1283,
        "y": 502,
        "t": 785
      }
    ]
  ]
}