{
  "label": "\\times",
  "timestamp": 1773052481588,
  "canvasWidth": 1536,
  "canvasHeight": 730,
  "strokes": [
    [
      {
        "x": 817,
        "y": 163,
        "t": 0
      },
      {
        "x": 817,
        "y": 167,
        "t": 16
      },
      {
        "x": 817,
        "y": 168,
        "t": 23
      },
      {
        "x": 822,
        "y": 175,
        "t": 34
      },
      {
        "x": 827,
        "y": 179,
        "t": 41
      },
      {
        "x": 827,
        "y": 179,
        "t": 47
      },
      {
        "x": 832,
        "y": 183,
        "t": 53
      },
      {
        "x": 836,
        "y": 187,
        "t": 62
      },
      {
        "x": 841,
        "y": 192,
        "t": 68
      },
      {
        "x": 841,
        "y": 192,
        "t": 74
      },
      {
        "x": 846,
        "y": 195,
        "t": 84
      },
      {
        "x": 848,
        "y": 196,
        "t": 89
      },
      {
        "x": 850,
        "y": 198,
        "t": 97
      },
      {
        "x": 850,
        "y": 199,
        "t": 100
      },
      {
        "x": 850,
        "y": 199,
        "t": 107
      },
      {
        "x": 850,
        "y": 199,
        "t": 127
      },
      {
        "x": 850,
        "y": 200,
        "t": 180
      },
      {
        "x": 850,
        "y": 199,
        "t": 204
      },
      {
        "x": 845,
        "y": 194,
        "t": 233
      }
    ],
    [
      {
        "x": 834,
        "y": 168,
        "t": 491
      },
      {
        "x": 834,
        "y": 170,
        "t": 495
      },
      {
        "x": 835,
        "y": 174,
        "t": 502
      },
      {
        "x": 837,
        "y": 180,
        "t": 510
      },
      {
        "x": 837,
        "y": 188,
        "t": 517
      },
      {
        "x": 837,
        "y": 196,
        "t": 526
      },
      {
        "x": 838,
        "y": 203,
        "t": 535
      },
      {
        "x": 838,
        "y": 209,
        "t": 539
      },
      {
        "x": 838,
        "y": 211,
        "t": 547
      },
      {
        "x": 838,
        "y": 214,
        "t": 553
      },
      {
        "x": 838,
        "y": 215,
        "t": 561
      },
      {
        "x": 837,
        "y": 215,
        "t": 633
      },
      {
        "x": 835,
        "y": 215,
        "t": 644
      }
    ]
  ]
}