{
  "label": "5",
  "timestamp": 1772383249323,
  "canvasWidth": 759,
  "canvasHeight": 794,
  "strokes": [
    [
      {
        "x": 383.712,
        "y": 50.524,
        "t": 0
      },
      {
        "x": 378.854,
        "y": 50.116,
        "t": 6
      },
      {
        "x": 374.973,
        "y": 51.458,
        "t": 23
      },
      {
        "x": 355.976,
        "y": 50.561,
        "t": 41
      },
      {
        "x": 335.803,
        "y": 59.239,
        "t": 60
      },
      {
        "x": 301.815,
        "y": 67.057,
        "t": 74
      },
      {
        "x": 260.977,
        "y": 73.638,
        "t": 90
      },
      {
        "x": 221.924,
        "y": 83.426,
        "t": 105
      },
      {
        "x": 192.417,
        "y": 82.612,
        "t": 122
      },
      {
        "x": 175.699,
        "y": 92.754,
        "t": 137
      },
      {
        "x": 173.707,
        "y": 94.144,
        "t": 237
      },
      {
        "x": 168.733,
        "y": 96.362,
        "t": 246
      },
      {
        "x": 174.51,
        "y": 102.682,
        "t": 261
      },
      {
        "x": 172.917,
        "y": 124.219,
        "t": 276
      },
      {
        "x": 173.639,
        "y": 132.938,
        "t": 288
      },
      {
        "x": 180.648,
        "y": 162.981,
        "t": 304
      },
      {
        "x": 185.723,
        "y": 178.086,
        "t": 321
      },
      {
        "x": 189.076,
        "y": 184.978,
        "t": 339
      },
      {
        "x": 187.437,
        "y": 188.618,
        "t": 357
      },
      {
        "x": 190.299,
        "y": 189.681,
        "t": 373
      },
      {
        "x": 187.672,
        "y": 192.252,
        "t": 388
      },
      {
        "x": 186.752,
        "y": 189.284,
        "t": 404
      },
      {
        "x": 192.99,
        "y": 194.798,
        "t": 488
      },
      {
        "x": 202.815,
        "y": 185.328,
        "t": 504
      },
      {
        "x": 207.203,
        "y": 190.574,
        "t": 521
      },
      {
        "x": 223.277,
        "y": 182.43,
        "t": 536
      },
      {
        "x": 241.075,
        "y": 178.572,
        "t": 552
      },
      {
        "x": 261.301,
        "y": 177.41,
        "t": 569
      },
      {
        "x": 280.367,
        "y": 172.601,
        "t": 585
      },
      {
        "x": 299.747,
        "y": 167.904,
        "t": 601
      },
      {
        "x": 314.455,
        "y": 173.272,
        "t": 617
      },
      {
        "x": 323.467,
        "y": 181.983,
        "t": 632
      },
      {
        "x": 331.942,
        "y": 192.649,
        "t": 649
      },
      {
        "x": 338.391,
        "y": 202.159,
        "t": 666
      },
      {
        "x": 343.087,
        "y": 213.294,
        "t": 682
      },
      {
        "x": 348.964,
        "y": 228.059,
        "t": 697
      },
      {
        "x": 350.344,
        "y": 234.181,
        "t": 712
      },
      {
        "x": 338.865,
        "y": 250.408,
        "t": 729
      },
      {
        "x": 327.943,
        "y": 268.368,
        "t": 745
      },
      {
        "x": 316.462,
        "y": 272.212,
        "t": 763
      },
      {
        "x": 290.164,
        "y": 279.768,
        "t": 779
      },
      {
        "x": 276.452,
        "y": 282.59,
        "t": 796
      },
      {
        "x": 262.408,
        "y": 284.583,
        "t": 812
      },
      {
        "x": 251.704,
        "y": 288.797,
        "t": 826
      },
      {
        "x": 249.77,
        "y": 285.721,
        "t": 844
      },
      {
        "x": 244.695,
        "y": 289.266,
        "t": 859
      },
      {
        "x": 241.402,
        "y": 289.73,
        "t": 908
      }
    ]
  ]
}